.DS_Store
more_node2vec/__init__.py
more_node2vec/api.py
more_node2vec/version.py
more_node2vec-0.0.5.dist-info/LICENSE
more_node2vec-0.0.5.dist-info/METADATA
more_node2vec-0.0.5.dist-info/WHEEL
more_node2vec-0.0.5.dist-info/top_level.txt
more_node2vec-0.0.5.dist-info/RECORD
