Metadata-Version: 2.1
Name: more-node2vec
Version: 0.0.5
Summary: Utilities for node2vec and gensim
Home-page: https://github.com/cthoyt/more-node2vec
Author: Charles Tapley Hoyt
Author-email: cthoyt@gmail.com
Maintainer: Charles Tapley Hoyt
Maintainer-email: cthoyt@gmail.com
License: MIT
Download-URL: https://github.com/cthoyt/more-node2vec/releases
Project-URL: Bug Tracker, https://github.com/cthoyt/more-node2vec/issues
Project-URL: Source Code, https://github.com/cthoyt/more-node2vec
Keywords: snekpack,cookiecutter,node2vec,nodevectors,deepwalk
Platform: UNKNOWN
Classifier: Development Status :: 1 - Planning
Classifier: Environment :: Console
Classifier: Intended Audience :: Developers
Classifier: License :: OSI Approved :: MIT License
Classifier: Operating System :: OS Independent
Classifier: Framework :: Pytest
Classifier: Framework :: tox
Classifier: Framework :: Sphinx
Classifier: Programming Language :: Python
Classifier: Programming Language :: Python :: 3.8
Classifier: Programming Language :: Python :: 3.9
Classifier: Programming Language :: Python :: 3 :: Only
Requires-Python: >=3.8
License-File: LICENSE
Requires-Dist: click
Requires-Dist: more-click
Requires-Dist: numpy
Requires-Dist: pandas
Requires-Dist: nodevectors
Requires-Dist: sklearn
Provides-Extra: docs
Requires-Dist: sphinx ; extra == 'docs'
Requires-Dist: sphinx-rtd-theme ; extra == 'docs'
Requires-Dist: sphinx-autodoc-typehints ; extra == 'docs'
Provides-Extra: tests
Requires-Dist: pytest ; extra == 'tests'
Requires-Dist: coverage ; extra == 'tests'
